ALGLIBConfig.cmake
include/lunasvg/lunasvg.h
include/plutovg/plutovg.h
includes/third_party/alglib/src/alglibinternal.h
includes/third_party/alglib/src/alglibmisc.h
includes/third_party/alglib/src/ap.h
includes/third_party/alglib/src/dataanalysis.h
includes/third_party/alglib/src/diffequations.h
includes/third_party/alglib/src/fasttransforms.h
includes/third_party/alglib/src/integration.h
includes/third_party/alglib/src/interpolation.h
includes/third_party/alglib/src/kernels_avx2.h
includes/third_party/alglib/src/kernels_fma.h
includes/third_party/alglib/src/kernels_sse2.h
includes/third_party/alglib/src/linalg.h
includes/third_party/alglib/src/optimization.h
includes/third_party/alglib/src/solvers.h
includes/third_party/alglib/src/specialfunctions.h
includes/third_party/alglib/src/statistics.h
includes/third_party/alglib/src/stdafx.h
includes/third_party/fmt/include/fmt/args.h
includes/third_party/fmt/include/fmt/base.h
includes/third_party/fmt/include/fmt/chrono.h
includes/third_party/fmt/include/fmt/color.h
includes/third_party/fmt/include/fmt/compile.h
includes/third_party/fmt/include/fmt/core.h
includes/third_party/fmt/include/fmt/format-inl.h
includes/third_party/fmt/include/fmt/format.h
includes/third_party/fmt/include/fmt/os.h
includes/third_party/fmt/include/fmt/ostream.h
includes/third_party/fmt/include/fmt/printf.h
includes/third_party/fmt/include/fmt/ranges.h
includes/third_party/fmt/include/fmt/std.h
includes/third_party/fmt/include/fmt/xchar.h
includes/third_party/fmt/test/fuzzing/fuzzer-common.h
includes/third_party/fmt/test/gtest/gmock/gmock.h
includes/third_party/fmt/test/gtest/gtest/gtest-spi.h
includes/third_party/fmt/test/gtest/gtest/gtest.h
includes/third_party/fmt/test/gtest-extra.h
includes/third_party/fmt/test/mock-allocator.h
includes/third_party/fmt/test/posix-mock.h
includes/third_party/fmt/test/scan.h
includes/third_party/fmt/test/test-assert.h
includes/third_party/fmt/test/util.h
includes/third_party/lunasvg/include/lunasvg.h
libgsp-0.0.0.dev0.dist-info/METADATA
libgsp-0.0.0.dev0.dist-info/WHEEL
libgsp-0.0.0.dev0.dist-info/entry_points.txt
libgsp-0.0.0.dev0.dist-info/RECORD
