Metadata-Version: 2.1
Name: libgsp
Version: 0.0.0.dev0
Summary: High-Performance Linear/Non-Linear Filters and Window Functions Library in C++ with Python Bindings
Author-Email: Mohammad Raziei <mohammadraziei1375@gmail.com>
Classifier: Development Status :: 4 - Beta
Classifier: License :: OSI Approved :: MIT License
Classifier: Operating System :: OS Independent
Classifier: Programming Language :: C++
Classifier: Programming Language :: Python :: Implementation :: CPython
Classifier: Programming Language :: Python :: 3 :: Only
Classifier: Programming Language :: Python :: 3.8
Classifier: Programming Language :: Python :: 3.9
Classifier: Programming Language :: Python :: 3.10
Classifier: Programming Language :: Python :: 3.11
Project-URL: Homepage, https://github.com/mohammadraziei/libgsp
Project-URL: Bug Tracker, https://github.com/mohammadraziei/libgsp/issues
Project-URL: Document, https://mohammadraziei.github.io/libgsp/latest
Requires-Python: >=3.8
Provides-Extra: test
Requires-Dist: pytest; extra == "test"
